WizzSoup.py
WizzSoup-1.dist-info/LICENSE.txt
WizzSoup-1.dist-info/METADATA
WizzSoup-1.dist-info/WHEEL
WizzSoup-1.dist-info/top_level.txt
WizzSoup-1.dist-info/RECORD
